newsmile/__init__.py
newsmile/decoder.py
newsmile/encoder.py
newsmile-1.1.dist-info/METADATA
newsmile-1.1.dist-info/WHEEL
newsmile-1.1.dist-info/licenses/LICENSE
newsmile-1.1.dist-info/RECORD
