Metadata-Version: 2.1
Name: newsmile
Version: 1.1
Summary: A Package containing tools for decoding/encoding Smile Format data to/from python object
Project-URL: Smile (data interchange format), https://en.wikipedia.org/wiki/Smile_%28data_interchange_format%29
Project-URL: Smile Format Specification, https://github.com/FasterXML/smile-format-specification
Author-email: Laurent Mornet <laurent.mornet@gmail.com>
License-File: LICENSE
Classifier: License :: OSI Approved :: MIT License
Classifier: Operating System :: OS Independent
Classifier: Programming Language :: Python :: 3
Requires-Python: >=3.7
